{
    "code": 0,
    "message": "Download success list",
    "data": [
        {
            "id": 1,
            "name": "Dan Truong",
            "age": 35
        },
        {
            "id": 2,
            "name": "Cam Ly",
            "age": 32
        },
        {
            "id": 3,
            "name": "Son Tung - MTP",
            "age": 20
        },
        {
            "id": 4,
            "name": "Ly Hai",
            "age": 45
        },
        {
            "id": 5,
            "name": "Le Quyen",
            "age": 40
        }
    ]
}